hatch_msgfmt/__about__.py
hatch_msgfmt/__init__.py
hatch_msgfmt/hooks.py
hatch_msgfmt/plugin.py
hatch_msgfmt/vendor/LICENSE
hatch_msgfmt/vendor/README.txt
hatch_msgfmt/vendor/__init__.py
hatch_msgfmt/vendor/msgfmt.py
hatch_msgfmt_s_ball-1.1.2.dist-info/METADATA
hatch_msgfmt_s_ball-1.1.2.dist-info/WHEEL
hatch_msgfmt_s_ball-1.1.2.dist-info/entry_points.txt
hatch_msgfmt_s_ball-1.1.2.dist-info/licenses/LICENSE.txt
hatch_msgfmt_s_ball-1.1.2.dist-info/RECORD
