Metadata-Version: 2.4
Name: hatch-msgfmt-s-ball
Version: 1.1.2
Summary: Automatically compile po files to mo ones at build time using msgfmt.py
Project-URL: Documentation, https://github.com/s-ball/hatch-msgfmt-s-ball#readme
Project-URL: Issues, https://github.com/s-ball/hatch-msgfmt-s-ball/issues
Project-URL: Source, https://github.com/s-ball/hatch-msgfmt-s-ball
Author-email: s-ball <s-ball@laposte.net>
License-Expression: MIT
License-File: LICENSE.txt
Classifier: Development Status :: 5 - Production/Stable
Classifier: Framework :: Hatch
Classifier: Intended Audience :: Developers
Classifier: Programming Language :: Python
Classifier: Programming Language :: Python :: 3.9
Classifier: Programming Language :: Python :: 3.10
Classifier: Programming Language :: Python :: 3.11
Classifier: Programming Language :: Python :: 3.12
Classifier: Programming Language :: Python :: 3.13
Classifier: Programming Language :: Python :: Implementation :: CPython
Classifier: Topic :: Software Development :: Build Tools
Classifier: Topic :: Software Development :: Localization
Requires-Python: >=3.9
Requires-Dist: hatchling
